RTL/all/fractionaln/hk_efm.v
`timescale  1ns / 1ps

module hk_efm #(
    parameter WIDTH = 24,  // 小数分频的位宽
    parameter A_GAIN = 1   // A = A_GAIN*2-1, 控制反馈的大小，具体原理去论文中看
) (
    input clk,             // 时钟输入
    input rst_n,           // 复位信号，低有效

    input [WIDTH-1:0] x_i, // 一阶的误差反馈调制器（EFM）的输入
    output y_o,            // 量化输出
    output [WIDTH-1:0] e_o // 误差输出，作为下一级 EFM 的输入
);

    wire [WIDTH:0] sum;
    reg [WIDTH:0] sum_r;

    // 实现一阶的误差反馈调制器的功能，具体原理去论文中看
    assign sum = x_i + sum_r[WIDTH-1:0];
    // assign sum = x_i + sum_r[WIDTH-1:0];

    // 对求和结果延迟一个时钟周期
    always @(posedge clk or negedge rst_n) begin
        if (!rst_n) begin
            sum_r <= 'b0;
        end else begin
            sum_r <= sum;
        end
    end

    // 原始输出
    assign e_o = sum_r[WIDTH-1:0];
    // assign y_o = sum[WIDTH];
    // 优化输出
    // 由于在 y 的输出上插入寄存器不会影响 Sigma-Delta 的传输函数，即不会影响 Sigma-Delta 的特性，因此将 y 用寄存器打一拍再输出，可以减少逻辑路径的长度，提高电路的频率
    assign y_o = sum_r[WIDTH];

endmodule

RTL/tb/tb_efm.v
`timescale  1ns / 1ps

module tb_efm;

// efm Parameters
parameter PERIOD = 10;
parameter WIDTH  = 9;

// efm Inputs
reg   clk                                  = 0 ;
reg   rst_n                                = 0 ;
reg   [WIDTH-1:0]  x_i                     = 0 ;

// efm Outputs
wire  y_o                                  ;
wire  [WIDTH-1:0]  e_o                     ;


initial
begin
    forever #(PERIOD/2)  clk=~clk;
end

initial
begin
    #(PERIOD*2) rst_n  =  1;
end

hk_efm #(
    .WIDTH ( WIDTH ))
 u_efm (
    .clk                     ( clk                ),
    .rst_n                   ( rst_n              ),
    .x_i                     ( x_i    [WIDTH-1:0] ),

    .y_o                     ( y_o                ),
    .e_o                     ( e_o    [WIDTH-1:0] )
);

initial
begin

	$dumpfile("efm.vcd");      // 指定输出文件名
    $dumpvars(0, tb_efm);
    x_i = 'd250;
    # (PERIOD*200);

    $finish;
end

endmodule

RTL/Fractional-N-DIV-master/delta-sigma/tb/efm.vcd
$date
	Mon Jul 06 10:42:47 2026
$end
$version
	Icarus Verilog
$end
$timescale
	1ps
$end
$scope module tb_efm $end
$var wire 1 ! y_o $end
$var wire 9 " e_o [8:0] $end
$var parameter 32 # PERIOD $end
$var parameter 32 $ WIDTH $end
$var reg 1 % clk $end
$var reg 1 & rst_n $end
$var reg 9 ' x_i [8:0] $end
$scope module u_efm $end
$var wire 1 % clk $end
$var wire 1 & rst_n $end
$var wire 9 ( x_i [8:0] $end
$var wire 1 ! y_o $end
$var wire 10 ) sum [9:0] $end
$var wire 9 * e_o [8:0] $end
$var parameter 32 + A_GAIN $end
$var parameter 32 , WIDTH $end
$var reg 10 - sum_r [9:0] $end
$upscope $end
$upscope $end
$enddefinitions $end
$comment Show the parameter values. $end
$dumpall
b1001 ,
b1 +
b1001 $
b1010 #
$end
#0
$dumpvars
b0 -
b11111010 *
b11111010 )
b11111010 (
b11111010 '
0&
0%
b11111010 "
0!
$end
#5000
1%
#10000
0%
#15000
1%
#20000
0%
1&
#25000
b111110100 "
b111110100 *
b111110100 )
b11111010 -
1%
#30000
0%
#35000
b11101110 "
b11101110 *
b1011101110 )
b111110100 -
1%
#40000
0%
#45000
b111100111 "
b111100111 *
b111100111 )
1!
b1011101110 -
1%
#50000
0%
#55000
b11100001 "
b11100001 *
b1011100001 )
0!
b111100111 -
1%
#60000
0%
#65000
b111011010 "
b111011010 *
b111011010 )
1!
b1011100001 -
1%
#70000
0%
#75000
b11010100 "
b11010100 *
b1011010100 )
0!
b111011010 -
1%
#80000
0%
#85000
b111001101 "
b111001101 *
b111001101 )
1!
b1011010100 -
1%
#90000
0%
#95000
b11000111 "
b11000111 *
b1011000111 )
0!
b111001101 -
1%
#100000
0%
#105000
b111000000 "
b111000000 *
b111000000 )
1!
b1011000111 -
1%
#110000
0%
#115000
b10111010 "
b10111010 *
b1010111010 )
0!
b111000000 -
1%
#120000
0%
#125000
b110110011 "
b110110011 *
b110110011 )
1!
b1010111010 -
1%
#130000
0%
#135000
b10101101 "
b10101101 *
b1010101101 )
0!
b110110011 -
1%
#140000
0%
#145000
b110100110 "
b110100110 *
b110100110 )
1!
b1010101101 -
1%
#150000
0%
#155000
b10100000 "
b10100000 *
b1010100000 )
0!
b110100110 -
1%
#160000
0%
#165000
b110011001 "
b110011001 *
b110011001 )
1!
b1010100000 -
1%
#170000
0%
#175000
b10010011 "
b10010011 *
b1010010011 )
0!
b110011001 -
1%
#180000
0%
#185000
b110001100 "
b110001100 *
b110001100 )
1!
b1010010011 -
1%
#190000
0%
#195000
b10000110 "
b10000110 *
b1010000110 )
0!
b110001100 -
1%
#200000
0%
#205000
b101111111 "
b101111111 *
b101111111 )
1!
b1010000110 -
1%
#210000
0%
#215000
b1111001 "
b1111001 *
b1001111001 )
0!
b101111111 -
1%
#220000
0%
#225000
b101110010 "
b101110010 *
b101110010 )
1!
b1001111001 -
1%
#230000
0%
#235000
b1101100 "
b1101100 *
b1001101100 )
0!
b101110010 -
1%
#240000
0%
#245000
b101100101 "
b101100101 *
b101100101 )
1!
b1001101100 -
1%
#250000
0%
#255000
b1011111 "
b1011111 *
b1001011111 )
0!
b101100101 -
1%
#260000
0%
#265000
b101011000 "
b101011000 *
b101011000 )
1!
b1001011111 -
1%
#270000
0%
#275000
b1010010 "
b1010010 *
b1001010010 )
0!
b101011000 -
1%
#280000
0%
#285000
b101001011 "
b101001011 *
b101001011 )
1!
b1001010010 -
1%
#290000
0%
#295000
b1000101 "
b1000101 *
b1001000101 )
0!
b101001011 -
1%
#300000
0%
#305000
b100111110 "
b100111110 *
b100111110 )
1!
b1001000101 -
1%
#310000
0%
#315000
b111000 "
b111000 *
b1000111000 )
0!
b100111110 -
1%
#320000
0%
#325000
b100110001 "
b100110001 *
b100110001 )
1!
b1000111000 -
1%
#330000
0%
#335000
b101011 "
b101011 *
b1000101011 )
0!
b100110001 -
1%
#340000
0%
#345000
b100100100 "
b100100100 *
b100100100 )
1!
b1000101011 -
1%
#350000
0%
#355000
b11110 "
b11110 *
b1000011110 )
0!
b100100100 -
1%
#360000
0%
#365000
b100010111 "
b100010111 *
b100010111 )
1!
b1000011110 -
1%
#370000
0%
#375000
b10001 "
b10001 *
b1000010001 )
0!
b100010111 -
1%
#380000
0%
#385000
b100001010 "
b100001010 *
b100001010 )
1!
b1000010001 -
1%
#390000
0%
#395000
b100 "
b100 *
b1000000100 )
0!
b100001010 -
1%
#400000
0%
#405000
b11111101 "
b11111101 *
b11111101 )
1!
b1000000100 -
1%
#410000
0%
#415000
b111110111 "
b111110111 *
b111110111 )
0!
b11111101 -
1%
#420000
0%
#425000
b11110001 "
b11110001 *
b1011110001 )
b111110111 -
1%
#430000
0%
#435000
b111101010 "
b111101010 *
b111101010 )
1!
b1011110001 -
1%
#440000
0%
#445000
b11100100 "
b11100100 *
b1011100100 )
0!
b111101010 -
1%
#450000
0%
#455000
b111011101 "
b111011101 *
b111011101 )
1!
b1011100100 -
1%
#460000
0%
#465000
b11010111 "
b11010111 *
b1011010111 )
0!
b111011101 -
1%
#470000
0%
#475000
b111010000 "
b111010000 *
b111010000 )
1!
b1011010111 -
1%
#480000
0%
#485000
b11001010 "
b11001010 *
b1011001010 )
0!
b111010000 -
1%
#490000
0%
#495000
b111000011 "
b111000011 *
b111000011 )
1!
b1011001010 -
1%
#500000
0%
#505000
b10111101 "
b10111101 *
b1010111101 )
0!
b111000011 -
1%
#510000
0%
#515000
b110110110 "
b110110110 *
b110110110 )
1!
b1010111101 -
1%
#520000
0%
#525000
b10110000 "
b10110000 *
b1010110000 )
0!
b110110110 -
1%
#530000
0%
#535000
b110101001 "
b110101001 *
b110101001 )
1!
b1010110000 -
1%
#540000
0%
#545000
b10100011 "
b10100011 *
b1010100011 )
0!
b110101001 -
1%
#550000
0%
#555000
b110011100 "
b110011100 *
b110011100 )
1!
b1010100011 -
1%
#560000
0%
#565000
b10010110 "
b10010110 *
b1010010110 )
0!
b110011100 -
1%
#570000
0%
#575000
b110001111 "
b110001111 *
b110001111 )
1!
b1010010110 -
1%
#580000
0%
#585000
b10001001 "
b10001001 *
b1010001001 )
0!
b110001111 -
1%
#590000
0%
#595000
b110000010 "
b110000010 *
b110000010 )
1!
b1010001001 -
1%
#600000
0%
#605000
b1111100 "
b1111100 *
b1001111100 )
0!
b110000010 -
1%
#610000
0%
#615000
b101110101 "
b101110101 *
b101110101 )
1!
b1001111100 -
1%
#620000
0%
#625000
b1101111 "
b1101111 *
b1001101111 )
0!
b101110101 -
1%
#630000
0%
#635000
b101101000 "
b101101000 *
b101101000 )
1!
b1001101111 -
1%
#640000
0%
#645000
b1100010 "
b1100010 *
b1001100010 )
0!
b101101000 -
1%
#650000
0%
#655000
b101011011 "
b101011011 *
b101011011 )
1!
b1001100010 -
1%
#660000
0%
#665000
b1010101 "
b1010101 *
b1001010101 )
0!
b101011011 -
1%
#670000
0%
#675000
b101001110 "
b101001110 *
b101001110 )
1!
b1001010101 -
1%
#680000
0%
#685000
b1001000 "
b1001000 *
b1001001000 )
0!
b101001110 -
1%
#690000
0%
#695000
b101000001 "
b101000001 *
b101000001 )
1!
b1001001000 -
1%
#700000
0%
#705000
b111011 "
b111011 *
b1000111011 )
0!
b101000001 -
1%
#710000
0%
#715000
b100110100 "
b100110100 *
b100110100 )
1!
b1000111011 -
1%
#720000
0%
#725000
b101110 "
b101110 *
b1000101110 )
0!
b100110100 -
1%
#730000
0%
#735000
b100100111 "
b100100111 *
b100100111 )
1!
b1000101110 -
1%
#740000
0%
#745000
b100001 "
b100001 *
b1000100001 )
0!
b100100111 -
1%
#750000
0%
#755000
b100011010 "
b100011010 *
b100011010 )
1!
b1000100001 -
1%
#760000
0%
#765000
b10100 "
b10100 *
b1000010100 )
0!
b100011010 -
1%
#770000
0%
#775000
b100001101 "
b100001101 *
b100001101 )
1!
b1000010100 -
1%
#780000
0%
#785000
b111 "
b111 *
b1000000111 )
0!
b100001101 -
1%
#790000
0%
#795000
b100000000 "
b100000000 *
b100000000 )
1!
b1000000111 -
1%
#800000
0%
#805000
b111111010 "
b111111010 *
b111111010 )
0!
b100000000 -
1%
#810000
0%
#815000
b11110100 "
b11110100 *
b1011110100 )
b111111010 -
1%
#820000
0%
#825000
b111101101 "
b111101101 *
b111101101 )
1!
b1011110100 -
1%
#830000
0%
#835000
b11100111 "
b11100111 *
b1011100111 )
0!
b111101101 -
1%
#840000
0%
#845000
b111100000 "
b111100000 *
b111100000 )
1!
b1011100111 -
1%
#850000
0%
#855000
b11011010 "
b11011010 *
b1011011010 )
0!
b111100000 -
1%
#860000
0%
#865000
b111010011 "
b111010011 *
b111010011 )
1!
b1011011010 -
1%
#870000
0%
#875000
b11001101 "
b11001101 *
b1011001101 )
0!
b111010011 -
1%
#880000
0%
#885000
b111000110 "
b111000110 *
b111000110 )
1!
b1011001101 -
1%
#890000
0%
#895000
b11000000 "
b11000000 *
b1011000000 )
0!
b111000110 -
1%
#900000
0%
#905000
b110111001 "
b110111001 *
b110111001 )
1!
b1011000000 -
1%
#910000
0%
#915000
b10110011 "
b10110011 *
b1010110011 )
0!
b110111001 -
1%
#920000
0%
#925000
b110101100 "
b110101100 *
b110101100 )
1!
b1010110011 -
1%
#930000
0%
#935000
b10100110 "
b10100110 *
b1010100110 )
0!
b110101100 -
1%
#940000
0%
#945000
b110011111 "
b110011111 *
b110011111 )
1!
b1010100110 -
1%
#950000
0%
#955000
b10011001 "
b10011001 *
b1010011001 )
0!
b110011111 -
1%
#960000
0%
#965000
b110010010 "
b110010010 *
b110010010 )
1!
b1010011001 -
1%
#970000
0%
#975000
b10001100 "
b10001100 *
b1010001100 )
0!
b110010010 -
1%
#980000
0%
#985000
b110000101 "
b110000101 *
b110000101 )
1!
b1010001100 -
1%
#990000
0%
#995000
b1111111 "
b1111111 *
b1001111111 )
0!
b110000101 -
1%
#1000000
0%
#1005000
b101111000 "
b101111000 *
b101111000 )
1!
b1001111111 -
1%
#1010000
0%
#1015000
b1110010 "
b1110010 *
b1001110010 )
0!
b101111000 -
1%
#1020000
0%
#1025000
b101101011 "
b101101011 *
b101101011 )
1!
b1001110010 -
1%
#1030000
0%
#1035000
b1100101 "
b1100101 *
b1001100101 )
0!
b101101011 -
1%
#1040000
0%
#1045000
b101011110 "
b101011110 *
b101011110 )
1!
b1001100101 -
1%
#1050000
0%
#1055000
b1011000 "
b1011000 *
b1001011000 )
0!
b101011110 -
1%
#1060000
0%
#1065000
b101010001 "
b101010001 *
b101010001 )
1!
b1001011000 -
1%
#1070000
0%
#1075000
b1001011 "
b1001011 *
b1001001011 )
0!
b101010001 -
1%
#1080000
0%
#1085000
b101000100 "
b101000100 *
b101000100 )
1!
b1001001011 -
1%
#1090000
0%
#1095000
b111110 "
b111110 *
b1000111110 )
0!
b101000100 -
1%
#1100000
0%
#1105000
b100110111 "
b100110111 *
b100110111 )
1!
b1000111110 -
1%
#1110000
0%
#1115000
b110001 "
b110001 *
b1000110001 )
0!
b100110111 -
1%
#1120000
0%
#1125000
b100101010 "
b100101010 *
b100101010 )
1!
b1000110001 -
1%
#1130000
0%
#1135000
b100100 "
b100100 *
b1000100100 )
0!
b100101010 -
1%
#1140000
0%
#1145000
b100011101 "
b100011101 *
b100011101 )
1!
b1000100100 -
1%
#1150000
0%
#1155000
b10111 "
b10111 *
b1000010111 )
0!
b100011101 -
1%
#1160000
0%
#1165000
b100010000 "
b100010000 *
b100010000 )
1!
b1000010111 -
1%
#1170000
0%
#1175000
b1010 "
b1010 *
b1000001010 )
0!
b100010000 -
1%
#1180000
0%
#1185000
b100000011 "
b100000011 *
b100000011 )
1!
b1000001010 -
1%
#1190000
0%
#1195000
b111111101 "
b111111101 *
b111111101 )
0!
b100000011 -
1%
#1200000
0%
#1205000
b11110111 "
b11110111 *
b1011110111 )
b111111101 -
1%
#1210000
0%
#1215000
b111110000 "
b111110000 *
b111110000 )
1!
b1011110111 -
1%
#1220000
0%
#1225000
b11101010 "
b11101010 *
b1011101010 )
0!
b111110000 -
1%
#1230000
0%
#1235000
b111100011 "
b111100011 *
b111100011 )
1!
b1011101010 -
1%
#1240000
0%
#1245000
b11011101 "
b11011101 *
b1011011101 )
0!
b111100011 -
1%
#1250000
0%
#1255000
b111010110 "
b111010110 *
b111010110 )
1!
b1011011101 -
1%
#1260000
0%
#1265000
b11010000 "
b11010000 *
b1011010000 )
0!
b111010110 -
1%
#1270000
0%
#1275000
b111001001 "
b111001001 *
b111001001 )
1!
b1011010000 -
1%
#1280000
0%
#1285000
b11000011 "
b11000011 *
b1011000011 )
0!
b111001001 -
1%
#1290000
0%
#1295000
b110111100 "
b110111100 *
b110111100 )
1!
b1011000011 -
1%
#1300000
0%
#1305000
b10110110 "
b10110110 *
b1010110110 )
0!
b110111100 -
1%
#1310000
0%
#1315000
b110101111 "
b110101111 *
b110101111 )
1!
b1010110110 -
1%
#1320000
0%
#1325000
b10101001 "
b10101001 *
b1010101001 )
0!
b110101111 -
1%
#1330000
0%
#1335000
b110100010 "
b110100010 *
b110100010 )
1!
b1010101001 -
1%
#1340000
0%
#1345000
b10011100 "
b10011100 *
b1010011100 )
0!
b110100010 -
1%
#1350000
0%
#1355000
b110010101 "
b110010101 *
b110010101 )
1!
b1010011100 -
1%
#1360000
0%
#1365000
b10001111 "
b10001111 *
b1010001111 )
0!
b110010101 -
1%
#1370000
0%
#1375000
b110001000 "
b110001000 *
b110001000 )
1!
b1010001111 -
1%
#1380000
0%
#1385000
b10000010 "
b10000010 *
b1010000010 )
0!
b110001000 -
1%
#1390000
0%
#1395000
b101111011 "
b101111011 *
b101111011 )
1!
b1010000010 -
1%
#1400000
0%
#1405000
b1110101 "
b1110101 *
b1001110101 )
0!
b101111011 -
1%
#1410000
0%
#1415000
b101101110 "
b101101110 *
b101101110 )
1!
b1001110101 -
1%
#1420000
0%
#1425000
b1101000 "
b1101000 *
b1001101000 )
0!
b101101110 -
1%
#1430000
0%
#1435000
b101100001 "
b101100001 *
b101100001 )
1!
b1001101000 -
1%
#1440000
0%
#1445000
b1011011 "
b1011011 *
b1001011011 )
0!
b101100001 -
1%
#1450000
0%
#1455000
b101010100 "
b101010100 *
b101010100 )
1!
b1001011011 -
1%
#1460000
0%
#1465000
b1001110 "
b1001110 *
b1001001110 )
0!
b101010100 -
1%
#1470000
0%
#1475000
b101000111 "
b101000111 *
b101000111 )
1!
b1001001110 -
1%
#1480000
0%
#1485000
b1000001 "
b1000001 *
b1001000001 )
0!
b101000111 -
1%
#1490000
0%
#1495000
b100111010 "
b100111010 *
b100111010 )
1!
b1001000001 -
1%
#1500000
0%
#1505000
b110100 "
b110100 *
b1000110100 )
0!
b100111010 -
1%
#1510000
0%
#1515000
b100101101 "
b100101101 *
b100101101 )
1!
b1000110100 -
1%
#1520000
0%
#1525000
b100111 "
b100111 *
b1000100111 )
0!
b100101101 -
1%
#1530000
0%
#1535000
b100100000 "
b100100000 *
b100100000 )
1!
b1000100111 -
1%
#1540000
0%
#1545000
b11010 "
b11010 *
b1000011010 )
0!
b100100000 -
1%
#1550000
0%
#1555000
b100010011 "
b100010011 *
b100010011 )
1!
b1000011010 -
1%
#1560000
0%
#1565000
b1101 "
b1101 *
b1000001101 )
0!
b100010011 -
1%
#1570000
0%
#1575000
b100000110 "
b100000110 *
b100000110 )
1!
b1000001101 -
1%
#1580000
0%
#1585000
b0 "
b0 *
b1000000000 )
0!
b100000110 -
1%
#1590000
0%
#1595000
b11111001 "
b11111001 *
b11111001 )
1!
b1000000000 -
1%
#1600000
0%
#1605000
b111110011 "
b111110011 *
b111110011 )
0!
b11111001 -
1%
#1610000
0%
#1615000
b11101101 "
b11101101 *
b1011101101 )
b111110011 -
1%
#1620000
0%
#1625000
b111100110 "
b111100110 *
b111100110 )
1!
b1011101101 -
1%
#1630000
0%
#1635000
b11100000 "
b11100000 *
b1011100000 )
0!
b111100110 -
1%
#1640000
0%
#1645000
b111011001 "
b111011001 *
b111011001 )
1!
b1011100000 -
1%
#1650000
0%
#1655000
b11010011 "
b11010011 *
b1011010011 )
0!
b111011001 -
1%
#1660000
0%
#1665000
b111001100 "
b111001100 *
b111001100 )
1!
b1011010011 -
1%
#1670000
0%
#1675000
b11000110 "
b11000110 *
b1011000110 )
0!
b111001100 -
1%
#1680000
0%
#1685000
b110111111 "
b110111111 *
b110111111 )
1!
b1011000110 -
1%
#1690000
0%
#1695000
b10111001 "
b10111001 *
b1010111001 )
0!
b110111111 -
1%
#1700000
0%
#1705000
b110110010 "
b110110010 *
b110110010 )
1!
b1010111001 -
1%
#1710000
0%
#1715000
b10101100 "
b10101100 *
b1010101100 )
0!
b110110010 -
1%
#1720000
0%
#1725000
b110100101 "
b110100101 *
b110100101 )
1!
b1010101100 -
1%
#1730000
0%
#1735000
b10011111 "
b10011111 *
b1010011111 )
0!
b110100101 -
1%
#1740000
0%
#1745000
b110011000 "
b110011000 *
b110011000 )
1!
b1010011111 -
1%
#1750000
0%
#1755000
b10010010 "
b10010010 *
b1010010010 )
0!
b110011000 -
1%
#1760000
0%
#1765000
b110001011 "
b110001011 *
b110001011 )
1!
b1010010010 -
1%
#1770000
0%
#1775000
b10000101 "
b10000101 *
b1010000101 )
0!
b110001011 -
1%
#1780000
0%
#1785000
b101111110 "
b101111110 *
b101111110 )
1!
b1010000101 -
1%
#1790000
0%
#1795000
b1111000 "
b1111000 *
b1001111000 )
0!
b101111110 -
1%
#1800000
0%
#1805000
b101110001 "
b101110001 *
b101110001 )
1!
b1001111000 -
1%
#1810000
0%
#1815000
b1101011 "
b1101011 *
b1001101011 )
0!
b101110001 -
1%
#1820000
0%
#1825000
b101100100 "
b101100100 *
b101100100 )
1!
b1001101011 -
1%
#1830000
0%
#1835000
b1011110 "
b1011110 *
b1001011110 )
0!
b101100100 -
1%
#1840000
0%
#1845000
b101010111 "
b101010111 *
b101010111 )
1!
b1001011110 -
1%
#1850000
0%
#1855000
b1010001 "
b1010001 *
b1001010001 )
0!
b101010111 -
1%
#1860000
0%
#1865000
b101001010 "
b101001010 *
b101001010 )
1!
b1001010001 -
1%
#1870000
0%
#1875000
b1000100 "
b1000100 *
b1001000100 )
0!
b101001010 -
1%
#1880000
0%
#1885000
b100111101 "
b100111101 *
b100111101 )
1!
b1001000100 -
1%
#1890000
0%
#1895000
b110111 "
b110111 *
b1000110111 )
0!
b100111101 -
1%
#1900000
0%
#1905000
b100110000 "
b100110000 *
b100110000 )
1!
b1000110111 -
1%
#1910000
0%
#1915000
b101010 "
b101010 *
b1000101010 )
0!
b100110000 -
1%
#1920000
0%
#1925000
b100100011 "
b100100011 *
b100100011 )
1!
b1000101010 -
1%
#1930000
0%
#1935000
b11101 "
b11101 *
b1000011101 )
0!
b100100011 -
1%
#1940000
0%
#1945000
b100010110 "
b100010110 *
b100010110 )
1!
b1000011101 -
1%
#1950000
0%
#1955000
b10000 "
b10000 *
b1000010000 )
0!
b100010110 -
1%
#1960000
0%
#1965000
b100001001 "
b100001001 *
b100001001 )
1!
b1000010000 -
1%
#1970000
0%
#1975000
b11 "
b11 *
b1000000011 )
0!
b100001001 -
1%
#1980000
0%
#1985000
b11111100 "
b11111100 *
b11111100 )
1!
b1000000011 -
1%
#1990000
0%
#1995000
b111110110 "
b111110110 *
b111110110 )
0!
b11111100 -
1%
