RTL/testbench/workbuddy/sim/idelaye3_stub.v
`timescale 1ns / 1ps
//////////////////////////////////////////////////////////////////////////////////
// Behavioral stub for IDELAYE3 (for iverilog simulation only).
// NOT synthesizable. Replaces the Xilinx UNISIM primitive so we can verify the
// loader FSM without Vivado. It latches CNTVALUEIN on the LOAD pulse (ASYNC) and
// applies a coarse delay = taps * 1ps to DATAIN so dout visibly lags din.
//////////////////////////////////////////////////////////////////////////////////
module IDELAYE3 #(
    parameter CASCADE       = "NONE",
    parameter DELAY_FORMAT  = "COUNT",
    parameter DELAY_SRC     = "DATAIN",
    parameter DELAY_TYPE    = "VAR_LOAD",
    parameter DELAY_VALUE   = 0,
    parameter IS_CLK_INVERTED = 1'b0,
    parameter IS_RST_INVERTED  = 1'b0,
    parameter real REFCLK_FREQUENCY = 300.0,
    parameter SIM_DEVICE    = "ULTRASCALE_PLUS",
    parameter UPDATE_MODE   = "ASYNC"
) (
    output wire        CASC_OUT,
    output wire [8:0]  CNTVALUEOUT,
    output wire        DATAOUT,
    input  wire        CASC_IN,
    input  wire        CASC_RETURN,
    input  wire        CE,
    input  wire        CLK,
    input  wire [8:0]  CNTVALUEIN,
    input  wire        DATAIN,
    input  wire        EN_VTC,
    input  wire        IDATAIN,
    input  wire        INC,
    input  wire        LOAD,
    input  wire        RST
);
    reg [8:0] taps;
    reg       dout_r;

    // ASYNC load: latch CNTVALUEIN on LOAD pulse.
    always @(posedge LOAD or posedge RST) begin
        if (RST)      taps <= 9'd0;
        else if (LOAD) taps <= CNTVALUEIN;
    end
    assign CNTVALUEOUT = taps;

    // Coarse behavioral delay: dout lags din by `taps` ps (1ps per tap in sim).
    always @(DATAIN or taps) begin
        #(taps) dout_r = (DELAY_SRC == "IDATAIN") ? IDATAIN : DATAIN;
    end
    assign DATAOUT = dout_r;

    assign CASC_OUT = 1'b0;
endmodule

RTL/testbench/workbuddy/src/dtc/idelay_dtc_top_fast.v
`timescale 1ns / 1ps
//////////////////////////////////////////////////////////////////////////////////
// Module: idelay_dtc_top_fast  (IDELAYE3 DTC, FAST + LARGE-JUMP optimized)
// Drop-in alternative to lut_dtc_top / idelay_dtc_top.
//
// DESIGN GOAL: fast settling + large code jumps, glitch-free to the PLL.
//
// HOW THIS MEETS "FAST + LARGE JUMP" (Xilinx AR#66013 / AR#67246 / UG861):
//   * VAR_LOAD hard limit: a SINGLE load may change the delay by at most 8
//     taps, or the line glitches (AR#66013: "maximum adjustment of 8 taps
//     only is permitted or the signal could glitch"). This is a PER-LOAD
//     limit, NOT a time limit -> the solution is NOT "wait", it is "step
//     every clock by <=8 taps".
//   * AR#66013 also says CNTVALUEIN adjustments are possible EVERY clock
//     cycle, and the new value takes effect the next clock cycle. So we
//     pipeline: one 8-tap step per idelay_clk, back-to-back, no inter-step
//     wait. (The 10/5-clock waits in AR#67246/UG861 are for toggling EN_VTC
//     for VT tracking -- we keep EN_VTC=0 / COUNT mode, so they do NOT apply.)
//   * FULL-RANGE (511 taps) @ 125 MHz idelay_clk = 64 steps * 8 ns = 512 ns.
//     @ 250 MHz = 256 ns. Fast enough for any PLL calibration loop.
//   * GATING DURING JUMP (AR#67246 "gate the clock during large adjustment",
//     adapted to component mode): the output MUX selects the delayed path
//     ONLY when `!busy` (settled). While ramping, dout = din (bypass), so the
//     64 intermediate steps never reach the PLL as glitches. This is the
//     component-mode equivalent of TBYTE_IN/TX_GATING.
//
// IMPORTANT: drive idelay_clk with a FAST clock (sys_clk, 125 MHz+).
//   idelay_clk is the LOADER clock, NOT the 12.5 MHz DTC output clock.
//   The 12.5 MHz DTC output is what flows through `din` -> delayed -> dout.
//
// MODE: UPDATE_MODE="ASYNC" + EN_VTC=0 + DELAY_FORMAT="COUNT" (no IDELAYCTRL).
//   ASYNC is required because SYNC forces LOAD=GND (REQP-1828) which cannot
//   load at all. ASYNC + LOAD pulse is legal and required.
//////////////////////////////////////////////////////////////////////////////////

module idelay_dtc_top_fast #(
    parameter N_TAP       = 512,
    parameter CODE_WIDTH  = 9,
    parameter MAIN_STAGES = 2,
    parameter MAX_STEP    = 8      // Xilinx hard limit: <=8 taps/load
) (
    input  wire              sys_clk,
    input  wire              rst_n,
    input  wire              din,
    input  wire [CODE_WIDTH-1:0] code,
    input  wire              cal_mode,
    input  wire [CODE_WIDTH-1:0] cal_code,
    input  wire              dtc_sel,
    input  wire              vco_clk,
    input  wire              idelay_en,    // 1=use delayed path, 0=bypass
    input  wire              idelay_clk,   // FAST loader clock (125 MHz+)
    output wire              dout,
    output wire [CODE_WIDTH-1:0] cal_result,
    output wire              cal_valid
);

    localparam STAGES = MAIN_STAGES;
    localparam integer MAX_STEP_I = MAX_STEP;   // signed-capable copy for compares

    // -------------------------------------------------------------------------
    // Stepwise ramp: move loaded_code toward code by <= MAX_STEP taps/step.
    // -------------------------------------------------------------------------
    reg [CODE_WIDTH-1:0] loaded_code;
    wire signed [CODE_WIDTH:0] diff = $signed({1'b0, code}) - $signed({1'b0, loaded_code});
    reg signed [4:0] step;
    always @(*) begin
        if      (diff >  MAX_STEP_I) step =  MAX_STEP_I[4:0];
        else if (diff < -MAX_STEP_I) step = -MAX_STEP_I[4:0];
        else                         step = diff[4:0];   // |diff| <= MAX_STEP -> 1 step
    end
    wire busy = (diff != 0);
    // next_val is combo, ready the whole cycle before LOAD asserts.
    wire [CODE_WIDTH-1:0] next_val = loaded_code + step;

    reg load_pulse;
    always @(posedge idelay_clk or negedge rst_n) begin
        if (~rst_n) begin
            loaded_code <= {CODE_WIDTH{1'b0}};
            load_pulse  <= 1'b0;
        end else begin
            // advance one (<=8-tap) step per clock, back-to-back.
            loaded_code <= busy ? next_val : loaded_code;
            load_pulse  <= busy;   // 1-clock LOAD pulse only while a step is pending
        end
    end

    // -------------------------------------------------------------------------
    // Fabric-chained IDELAYE3 delay line (CASCADE="NONE", no LOC, no Route 35-19).
    // -------------------------------------------------------------------------
    wire [STAGES-1:0] main_do;

    genvar s;
    generate
        for (s = 0; s < STAGES; s = s + 1) begin : main_delay
            IDELAYE3 #(
                .CASCADE("NONE"), .DELAY_FORMAT("COUNT"), .DELAY_SRC("DATAIN"),
                .DELAY_TYPE("VAR_LOAD"), .DELAY_VALUE(0), .IS_CLK_INVERTED(1'b0),
                .IS_RST_INVERTED(1'b0),                 .REFCLK_FREQUENCY(300.0),
                .SIM_DEVICE("ULTRASCALE_PLUS"), .UPDATE_MODE("ASYNC")
            ) u_idelay (
                .CLK(idelay_clk), .CE(1'b0), .INC(1'b0),
                .CASC_IN(1'b0), .CASC_RETURN(1'b0), .CASC_OUT(),
                .IDATAIN(1'b0),
                .DATAIN((s == 0) ? din : main_do[s-1]),
                .LOAD(load_pulse),
                .CNTVALUEIN(next_val),
                .CNTVALUEOUT(), .DATAOUT(main_do[s]),
                .EN_VTC(1'b0), .RST(~rst_n)
            );
        end
    endgenerate

    // -------------------------------------------------------------------------
    // Auto-gate during ramp: only select the delayed path when settled.
    // While busy, output = din (raw, glitch-free); when settled, = delayed.
    // This hides the intermediate steps from the PLL (AR#67246 technique).
    // -------------------------------------------------------------------------
    assign dout = (idelay_en && !busy) ? main_do[STAGES-1] : din;

    // calibration ports kept for interface compatibility (no-op in this build)
    assign cal_result = {CODE_WIDTH{1'b0}};
    assign cal_valid  = 1'b0;

endmodule

RTL/testbench/workbuddy/sim/idelay_dtc_top_fast_tb.v
`timescale 1ns / 1ps
module idelay_dtc_top_fast_tb;

    // FAST loader clock = 125 MHz (8 ns). The 12.5 MHz DTC output is the DATA
    // flowing through din, NOT this clock.
    reg idelay_clk = 0;
    always #4 idelay_clk = ~idelay_clk;   // 125 MHz

    reg sys_clk = 0;
    always #4 sys_clk = ~sys_clk;

    reg rst_n = 0;
    reg din = 0;
    // emulate a 12.5 MHz DTC output clock on din
    always #40 din = ~din;

    reg [8:0] code = 0;
    reg idelay_en = 1;

    wire dout;
    wire [8:0] cal_result;
    wire cal_valid;

    idelay_dtc_top_fast #(
        .CODE_WIDTH(9), .MAIN_STAGES(2), .MAX_STEP(8)
    ) dut (
        .sys_clk(sys_clk), .rst_n(rst_n), .din(din), .code(code),
        .cal_mode(1'b0), .cal_code(9'd0), .dtc_sel(1'b0), .vco_clk(1'b0),
        .idelay_en(idelay_en), .idelay_clk(idelay_clk),
        .dout(dout), .cal_result(cal_result), .cal_valid(cal_valid)
    );

    // monitor the internal busy + loaded_code via hierarchical refs
    wire [8:0] loaded_code = dut.loaded_code;
    wire busy = dut.busy;
    wire load_pulse = dut.load_pulse;

    integer clk_cnt;
    initial begin
        $dumpfile("sim/idelay_fast.vcd");
        $dumpvars(0);
        #100 rst_n = 1;
        code = 9'd300;   // large jump 0 -> 300 (300 taps)
        clk_cnt = 0;
        // wait until settled
        while (busy && clk_cnt < 200) begin @(posedge idelay_clk); clk_cnt++; end
        $display("JUMP 0->300 : settled in %0d loader-clks (%0d ns)  loaded=%0d busy=%b",
                 clk_cnt, clk_cnt*8, loaded_code, busy);

        code = 9'd0;     // large jump back 300 -> 0 (crosses 256)
        clk_cnt = 0;
        while (busy && clk_cnt < 200) begin @(posedge idelay_clk); clk_cnt++; end
        $display("JUMP 300->0 : settled in %0d loader-clks (%0d ns)  loaded=%0d busy=%b",
                 clk_cnt, clk_cnt*8, loaded_code, busy);

        code = 9'd511;   // full-range jump
        clk_cnt = 0;
        while (busy && clk_cnt < 300) begin @(posedge idelay_clk); clk_cnt++; end
        $display("JUMP 0->511 : settled in %0d loader-clks (%0d ns)  loaded=%0d busy=%b",
                 clk_cnt, clk_cnt*8, loaded_code, busy);

        $display("CONVERGENCE OK (busy=0 at end, loaded==code)");
        $finish;
    end

endmodule

RTL/testbench/workbuddy/sim/idelay_fast.vcd
$date
	Thu Jul 30 21:18:44 2026
$end
$version
	Icarus Verilog
$end
$timescale
	1ps
$end
$scope module idelay_dtc_top_fast_tb $end
$var wire 1 ! busy $end
$var wire 9 " cal_result [8:0] $end
$var wire 1 # cal_valid $end
$var wire 1 $ load_pulse $end
$var wire 9 % loaded_code [8:0] $end
$var wire 1 & dout $end
$var reg 9 ' code [8:0] $end
$var reg 1 ( din $end
$var reg 1 ) idelay_clk $end
$var reg 1 * idelay_en $end
$var reg 1 + rst_n $end
$var reg 1 , sys_clk $end
$var integer 32 - clk_cnt [31:0] $end
$scope module dut $end
$var wire 9 . cal_code [8:0] $end
$var wire 1 / cal_mode $end
$var wire 9 0 cal_result [8:0] $end
$var wire 1 # cal_valid $end
$var wire 9 1 code [8:0] $end
$var wire 1 ( din $end
$var wire 1 2 dtc_sel $end
$var wire 1 ) idelay_clk $end
$var wire 1 * idelay_en $end
$var wire 1 + rst_n $end
$var wire 1 , sys_clk $end
$var wire 1 3 vco_clk $end
$var wire 9 4 next_val [8:0] $end
$var wire 2 5 main_do [1:0] $end
$var wire 1 & dout $end
$var wire 10 6 diff [9:0] $end
$var wire 1 7 busy $end
$var parameter 32 8 CODE_WIDTH $end
$var parameter 32 9 MAIN_STAGES $end
$var parameter 32 : MAX_STEP $end
$var parameter 32 ; MAX_STEP_I $end
$var parameter 32 < N_TAP $end
$var parameter 32 = STAGES $end
$var reg 1 > load_pulse $end
$var reg 9 ? loaded_code [8:0] $end
$var reg 5 @ step [4:0] $end
$scope begin main_delay[0] $end
$var parameter 2 A s $end
$scope module u_idelay $end
$var wire 1 B CASC_IN $end
$var wire 1 C CASC_OUT $end
$var wire 1 D CASC_RETURN $end
$var wire 1 E CE $end
$var wire 1 ) CLK $end
$var wire 9 F CNTVALUEIN [8:0] $end
$var wire 9 G CNTVALUEOUT [8:0] $end
$var wire 1 ( DATAIN $end
$var wire 1 H EN_VTC $end
$var wire 1 I IDATAIN $end
$var wire 1 J INC $end
$var wire 1 > LOAD $end
$var wire 1 K RST $end
$var wire 1 L DATAOUT $end
$var parameter 32 M CASCADE $end
$var parameter 40 N DELAY_FORMAT $end
$var parameter 48 O DELAY_SRC $end
$var parameter 64 P DELAY_TYPE $end
$var parameter 32 Q DELAY_VALUE $end
$var parameter 1 R IS_CLK_INVERTED $end
$var parameter 1 S IS_RST_INVERTED $end
$var real 1 T REFCLK_FREQUENCY $end
$var parameter 120 U SIM_DEVICE $end
$var parameter 40 V UPDATE_MODE $end
$var reg 1 L dout_r $end
$var reg 9 W taps [8:0] $end
$upscope $end
$upscope $end
$scope begin main_delay[1] $end
$var parameter 2 X s $end
$scope module u_idelay $end
$var wire 1 Y CASC_IN $end
$var wire 1 Z CASC_OUT $end
$var wire 1 [ CASC_RETURN $end
$var wire 1 \ CE $end
$var wire 1 ) CLK $end
$var wire 9 ] CNTVALUEIN [8:0] $end
$var wire 9 ^ CNTVALUEOUT [8:0] $end
$var wire 1 _ DATAIN $end
$var wire 1 ` EN_VTC $end
$var wire 1 a IDATAIN $end
$var wire 1 b INC $end
$var wire 1 > LOAD $end
$var wire 1 c RST $end
$var wire 1 d DATAOUT $end
$var parameter 32 e CASCADE $end
$var parameter 40 f DELAY_FORMAT $end
$var parameter 48 g DELAY_SRC $end
$var parameter 64 h DELAY_TYPE $end
$var parameter 32 i DELAY_VALUE $end
$var parameter 1 j IS_CLK_INVERTED $end
$var parameter 1 k IS_RST_INVERTED $end
$var real 1 l REFCLK_FREQUENCY $end
$var parameter 120 m SIM_DEVICE $end
$var parameter 40 n UPDATE_MODE $end
$var reg 1 d dout_r $end
$var reg 9 o taps [8:0] $end
$upscope $end
$upscope $end
$upscope $end
$upscope $end
$enddefinitions $end
$comment Show the parameter values. $end
$dumpall
b100000101010011010110010100111001000011 n
b10101010100110001010100010100100100000101010011010000110100000101001100010001010101111101010000010011000101010101010011 m
r300 l
0k
0j
b0 i
b101011001000001010100100101111101001100010011110100000101000100 h
b10001000100000101010100010000010100100101001110 g
b100001101001111010101010100111001010100 f
b1001110010011110100111001000101 e
b1 X
b100000101010011010110010100111001000011 V
b10101010100110001010100010100100100000101010011010000110100000101001100010001010101111101010000010011000101010101010011 U
r300 T
0S
0R
b0 Q
b101011001000001010100100101111101001100010011110100000101000100 P
b10001000100000101010100010000010100100101001110 O
b100001101001111010101010100111001010100 N
b1001110010011110100111001000101 M
b0 A
b10 =
b1000000000 <
b1000 ;
b1000 :
b10 9
b1001 8
$end
#0
$dumpvars
bx o
xd
1c
0b
0a
0`
x_
bx ^
bx ]
0\
0[
0Z
0Y
bx W
xL
1K
0J
0I
0H
bx G
bx F
0E
0D
0C
0B
bx @
bx ?
x>
x7
bx 6
bx 5
bx 4
03
02
b0 1
b0 0
0/
b0 .
bx -
0,
0+
1*
0)
0(
b0 '
x&
bx %
x$
0#
b0 "
x!
$end
#4000
b0 4
b0 F
b0 ]
b0 @
0$
0>
0!
07
b0 6
b0 %
b0 ?
1,
1)
#8000
0,
0)
#12000
1,
1)
#16000
0,
0)
#20000
1,
1)
#24000
0,
0)
#28000
1,
1)
#32000
0,
0)
#36000
1,
1)
#40000
1&
1d
1_
b11 5
1L
0,
0)
1(
#44000
1,
1)
#48000
0,
0)
#52000
1,
1)
#56000
0,
0)
#60000
1,
1)
#64000
0,
0)
#68000
1,
1)
#72000
0,
0)
#76000
1,
1)
#80000
0&
0d
0_
b0 5
0L
0,
0)
0(
#84000
1,
1)
#88000
0,
0)
#92000
1,
1)
#96000
0,
0)
#100000
b10000 G
b10000 W
b10000 ^
b10000 o
1$
1>
b1000 %
b1000 ?
b10000 4
b10000 F
b10000 ]
b1000 @
0K
0c
1,
1)
b1 -
1!
17
b100100100 6
b100101100 '
b100101100 1
1+
#104000
0,
0)
#108000
b100011100 6
b11000 4
b11000 F
b11000 ]
b10000 %
b10000 ?
b10 -
1,
1)
#112000
0,
0)
#116000
b100010100 6
b100000 4
b100000 F
b100000 ]
b11000 %
b11000 ?
b11 -
1,
1)
#120000
1&
0,
0)
1(
#124000
b100001100 6
b101000 4
b101000 F
b101000 ]
b100000 %
b100000 ?
b100 -
1,
1)
#128000
0,
0)
#132000
b100000100 6
b110000 4
b110000 F
b110000 ]
b101000 %
b101000 ?
b101 -
1,
1)
#136000
1_
0,
0)
b1 5
1L
#140000
b11111100 6
b111000 4
b111000 F
b111000 ]
b110000 %
b110000 ?
b110 -
1,
1)
#144000
0,
0)
#148000
b11110100 6
b1000000 4
b1000000 F
b1000000 ]
b111000 %
b111000 ?
b111 -
1,
1)
#152000
0,
0)
b11 5
1d
#156000
b11101100 6
b1001000 4
b1001000 F
b1001000 ]
b1000000 %
b1000000 ?
b1000 -
1,
1)
#160000
0&
0,
0)
0(
#164000
b11100100 6
b1010000 4
b1010000 F
b1010000 ]
b1001000 %
b1001000 ?
b1001 -
1,
1)
#168000
0,
0)
#172000
b11011100 6
b1011000 4
b1011000 F
b1011000 ]
b1010000 %
b1010000 ?
b1010 -
1,
1)
#176000
0_
0,
0)
b10 5
0L
#180000
b11010100 6
b1100000 4
b1100000 F
b1100000 ]
b1011000 %
b1011000 ?
b1011 -
1,
1)
#184000
0,
0)
#188000
b11001100 6
b1101000 4
b1101000 F
b1101000 ]
b1100000 %
b1100000 ?
b1100 -
1,
1)
#192000
0,
0)
b0 5
0d
#196000
b11000100 6
b1110000 4
b1110000 F
b1110000 ]
b1101000 %
b1101000 ?
b1101 -
1,
1)
#200000
1&
0,
0)
1(
#204000
b10111100 6
b1111000 4
b1111000 F
b1111000 ]
b1110000 %
b1110000 ?
b1110 -
1,
1)
#208000
0,
0)
#212000
b10110100 6
b10000000 4
b10000000 F
b10000000 ]
b1111000 %
b1111000 ?
b1111 -
1,
1)
#216000
1_
0,
0)
b1 5
1L
#220000
b10101100 6
b10001000 4
b10001000 F
b10001000 ]
b10000000 %
b10000000 ?
b10000 -
1,
1)
#224000
0,
0)
#228000
b10100100 6
b10010000 4
b10010000 F
b10010000 ]
b10001000 %
b10001000 ?
b10001 -
1,
1)
#232000
0,
0)
b11 5
1d
#236000
b10011100 6
b10011000 4
b10011000 F
b10011000 ]
b10010000 %
b10010000 ?
b10010 -
1,
1)
#240000
0&
0,
0)
0(
#244000
b10010100 6
b10100000 4
b10100000 F
b10100000 ]
b10011000 %
b10011000 ?
b10011 -
1,
1)
#248000
0,
0)
#252000
b10001100 6
b10101000 4
b10101000 F
b10101000 ]
b10100000 %
b10100000 ?
b10100 -
1,
1)
#256000
0_
0,
0)
b10 5
0L
#260000
b10000100 6
b10110000 4
b10110000 F
b10110000 ]
b10101000 %
b10101000 ?
b10101 -
1,
1)
#264000
0,
0)
#268000
b1111100 6
b10111000 4
b10111000 F
b10111000 ]
b10110000 %
b10110000 ?
b10110 -
1,
1)
#272000
0,
0)
b0 5
0d
#276000
b1110100 6
b11000000 4
b11000000 F
b11000000 ]
b10111000 %
b10111000 ?
b10111 -
1,
1)
#280000
1&
0,
0)
1(
#284000
b1101100 6
b11001000 4
b11001000 F
b11001000 ]
b11000000 %
b11000000 ?
b11000 -
1,
1)
#288000
0,
0)
#292000
b1100100 6
b11010000 4
b11010000 F
b11010000 ]
b11001000 %
b11001000 ?
b11001 -
1,
1)
#296000
1_
0,
0)
b1 5
1L
#300000
b1011100 6
b11011000 4
b11011000 F
b11011000 ]
b11010000 %
b11010000 ?
b11010 -
1,
1)
#304000
0,
0)
#308000
b1010100 6
b11100000 4
b11100000 F
b11100000 ]
b11011000 %
b11011000 ?
b11011 -
1,
1)
#312000
0,
0)
b11 5
1d
#316000
b1001100 6
b11101000 4
b11101000 F
b11101000 ]
b11100000 %
b11100000 ?
b11100 -
1,
1)
#320000
0&
0,
0)
0(
#324000
b1000100 6
b11110000 4
b11110000 F
b11110000 ]
b11101000 %
b11101000 ?
b11101 -
1,
1)
#328000
0,
0)
#332000
b111100 6
b11111000 4
b11111000 F
b11111000 ]
b11110000 %
b11110000 ?
b11110 -
1,
1)
#336000
0_
0,
0)
b10 5
0L
#340000
b110100 6
b100000000 4
b100000000 F
b100000000 ]
b11111000 %
b11111000 ?
b11111 -
1,
1)
#344000
0,
0)
#348000
b101100 6
b100001000 4
b100001000 F
b100001000 ]
b100000000 %
b100000000 ?
b100000 -
1,
1)
#352000
0,
0)
b0 5
0d
#356000
b100100 6
b100010000 4
b100010000 F
b100010000 ]
b100001000 %
b100001000 ?
b100001 -
1,
1)
#360000
1&
0,
0)
1(
#364000
b11100 6
b100011000 4
b100011000 F
b100011000 ]
b100010000 %
b100010000 ?
b100010 -
1,
1)
#368000
0,
0)
#372000
b10100 6
b100100000 4
b100100000 F
b100100000 ]
b100011000 %
b100011000 ?
b100011 -
1,
1)
#376000
1_
0,
0)
b1 5
1L
#380000
b1100 6
b100101000 4
b100101000 F
b100101000 ]
b100100000 %
b100100000 ?
b100100 -
1,
1)
#384000
0,
0)
#388000
b100 @
b100 6
b100101100 4
b100101100 F
b100101100 ]
b100101000 %
b100101000 ?
b100101 -
1,
1)
#392000
0,
0)
b11 5
1d
#396000
b0 @
0!
07
b0 6
b100101100 4
b100101100 F
b100101100 ]
b100101100 %
b100101100 ?
b100110 -
1,
1)
#400000
0,
0)
0(
#404000
0&
b101000100 4
b101000100 F
b101000100 ]
b11000 @
1!
17
b1011010100 6
b0 '
b0 1
b0 -
1,
1)
#408000
0,
0)
#412000
b1010111100 6
b101011100 4
b101011100 F
b101011100 ]
b101000100 %
b101000100 ?
b1 -
1,
1)
#416000
0_
0,
0)
b10 5
0L
#420000
b1010100100 6
b101110100 4
b101110100 F
b101110100 ]
b101011100 %
b101011100 ?
b10 -
1,
1)
#424000
0,
0)
#428000
b1010001100 6
b110001100 4
b110001100 F
b110001100 ]
b101110100 %
b101110100 ?
b11 -
1,
1)
#432000
0,
0)
b0 5
0d
#436000
b1001110100 6
b110100100 4
b110100100 F
b110100100 ]
b110001100 %
b110001100 ?
b100 -
1,
1)
#440000
1&
0,
0)
1(
#444000
b1001011100 6
b110111100 4
b110111100 F
b110111100 ]
b110100100 %
b110100100 ?
b101 -
1,
1)
#448000
0,
0)
#452000
b1001000100 6
b111010100 4
b111010100 F
b111010100 ]
b110111100 %
b110111100 ?
b110 -
1,
1)
#456000
1_
0,
0)
b1 5
1L
#460000
b1000101100 6
b111101100 4
b111101100 F
b111101100 ]
b111010100 %
b111010100 ?
b111 -
1,
1)
#464000
0,
0)
#468000
b1000010100 6
b100 4
b100 F
b100 ]
b111101100 %
b111101100 ?
b1000 -
1,
1)
#472000
0,
0)
b11 5
1d
#476000
b11100 @
b1111111100 6
b100000 4
b100000 F
b100000 ]
b100 %
b100 ?
b1001 -
1,
1)
#480000
0&
0,
0)
0(
#484000
b11000 @
b1111100000 6
b111000 4
b111000 F
b111000 ]
b100000 %
b100000 ?
b1010 -
1,
1)
#488000
0,
0)
#492000
b1111001000 6
b1010000 4
b1010000 F
b1010000 ]
b111000 %
b111000 ?
b1011 -
1,
1)
#496000
0_
0,
0)
b10 5
0L
#500000
b1110110000 6
b1101000 4
b1101000 F
b1101000 ]
b1010000 %
b1010000 ?
b1100 -
1,
1)
#504000
0,
0)
#508000
b1110011000 6
b10000000 4
b10000000 F
b10000000 ]
b1101000 %
b1101000 ?
b1101 -
1,
1)
#512000
0,
0)
b0 5
0d
#516000
b1110000000 6
b10011000 4
b10011000 F
b10011000 ]
b10000000 %
b10000000 ?
b1110 -
1,
1)
#520000
1&
0,
0)
1(
#524000
b1101101000 6
b10110000 4
b10110000 F
b10110000 ]
b10011000 %
b10011000 ?
b1111 -
1,
1)
#528000
0,
0)
#532000
b1101010000 6
b11001000 4
b11001000 F
b11001000 ]
b10110000 %
b10110000 ?
b10000 -
1,
1)
#536000
1_
0,
0)
b1 5
1L
#540000
b1100111000 6
b11100000 4
b11100000 F
b11100000 ]
b11001000 %
b11001000 ?
b10001 -
1,
1)
#544000
0,
0)
#548000
b1100100000 6
b11111000 4
b11111000 F
b11111000 ]
b11100000 %
b11100000 ?
b10010 -
1,
1)
#552000
0,
0)
b11 5
1d
#556000
b1100001000 6
b100010000 4
b100010000 F
b100010000 ]
b11111000 %
b11111000 ?
b10011 -
1,
1)
#560000
0&
0,
0)
0(
#564000
b1011110000 6
b100101000 4
b100101000 F
b100101000 ]
b100010000 %
b100010000 ?
b10100 -
1,
1)
#568000
0,
0)
#572000
b1011011000 6
b101000000 4
b101000000 F
b101000000 ]
b100101000 %
b100101000 ?
b10101 -
1,
1)
#576000
0_
0,
0)
b10 5
0L
#580000
b1011000000 6
b101011000 4
b101011000 F
b101011000 ]
b101000000 %
b101000000 ?
b10110 -
1,
1)
#584000
0,
0)
#588000
b1010101000 6
b101110000 4
b101110000 F
b101110000 ]
b101011000 %
b101011000 ?
b10111 -
1,
1)
#592000
0,
0)
b0 5
0d
#596000
b1010010000 6
b110001000 4
b110001000 F
b110001000 ]
b101110000 %
b101110000 ?
b11000 -
1,
1)
#600000
1&
0,
0)
1(
#604000
b1001111000 6
b110100000 4
b110100000 F
b110100000 ]
b110001000 %
b110001000 ?
b11001 -
1,
1)
#608000
0,
0)
#612000
b1001100000 6
b110111000 4
b110111000 F
b110111000 ]
b110100000 %
b110100000 ?
b11010 -
1,
1)
#616000
1_
0,
0)
b1 5
1L
#620000
b1001001000 6
b111010000 4
b111010000 F
b111010000 ]
b110111000 %
b110111000 ?
b11011 -
1,
1)
#624000
0,
0)
#628000
b1000110000 6
b111101000 4
b111101000 F
b111101000 ]
b111010000 %
b111010000 ?
b11100 -
1,
1)
#632000
0,
0)
b11 5
1d
#636000
b1000011000 6
b0 4
b0 F
b0 ]
b111101000 %
b111101000 ?
b11101 -
1,
1)
#640000
0&
0,
0)
0(
#644000
1&
b0 @
0!
07
b0 6
b0 4
b0 F
b0 ]
b0 %
b0 ?
b11110 -
1,
1)
#648000
0,
0)
#652000
0&
b1000 4
b1000 F
b1000 ]
b1000 @
1!
17
b111111111 6
b111111111 '
b111111111 1
b0 -
1,
1)
#656000
0_
0,
0)
b10 5
0L
#660000
b111110111 6
b10000 4
b10000 F
b10000 ]
b1000 %
b1000 ?
b1 -
1,
1)
#664000
0,
0)
#668000
b111101111 6
b11000 4
b11000 F
b11000 ]
b10000 %
b10000 ?
b10 -
1,
1)
#672000
0,
0)
b0 5
0d
#676000
b111100111 6
b100000 4
b100000 F
b100000 ]
b11000 %
b11000 ?
b11 -
1,
1)
#680000
1&
0,
0)
1(
#684000
b111011111 6
b101000 4
b101000 F
b101000 ]
b100000 %
b100000 ?
b100 -
1,
1)
#688000
0,
0)
#692000
b111010111 6
b110000 4
b110000 F
b110000 ]
b101000 %
b101000 ?
b101 -
1,
1)
#696000
1_
0,
0)
b1 5
1L
#700000
b111001111 6
b111000 4
b111000 F
b111000 ]
b110000 %
b110000 ?
b110 -
1,
1)
#704000
0,
0)
#708000
b111000111 6
b1000000 4
b1000000 F
b1000000 ]
b111000 %
b111000 ?
b111 -
1,
1)
#712000
0,
0)
b11 5
1d
#716000
b110111111 6
b1001000 4
b1001000 F
b1001000 ]
b1000000 %
b1000000 ?
b1000 -
1,
1)
#720000
0&
0,
0)
0(
#724000
b110110111 6
b1010000 4
b1010000 F
b1010000 ]
b1001000 %
b1001000 ?
b1001 -
1,
1)
#728000
0,
0)
#732000
b110101111 6
b1011000 4
b1011000 F
b1011000 ]
b1010000 %
b1010000 ?
b1010 -
1,
1)
#736000
0_
0,
0)
b10 5
0L
#740000
b110100111 6
b1100000 4
b1100000 F
b1100000 ]
b1011000 %
b1011000 ?
b1011 -
1,
1)
#744000
0,
0)
#748000
b110011111 6
b1101000 4
b1101000 F
b1101000 ]
b1100000 %
b1100000 ?
b1100 -
1,
1)
#752000
0,
0)
b0 5
0d
#756000
b110010111 6
b1110000 4
b1110000 F
b1110000 ]
b1101000 %
b1101000 ?
b1101 -
1,
1)
#760000
1&
0,
0)
1(
#764000
b110001111 6
b1111000 4
b1111000 F
b1111000 ]
b1110000 %
b1110000 ?
b1110 -
1,
1)
#768000
0,
0)
#772000
b110000111 6
b10000000 4
b10000000 F
b10000000 ]
b1111000 %
b1111000 ?
b1111 -
1,
1)
#776000
1_
0,
0)
b1 5
1L
#780000
b101111111 6
b10001000 4
b10001000 F
b10001000 ]
b10000000 %
b10000000 ?
b10000 -
1,
1)
#784000
0,
0)
#788000
b101110111 6
b10010000 4
b10010000 F
b10010000 ]
b10001000 %
b10001000 ?
b10001 -
1,
1)
#792000
0,
0)
b11 5
1d
#796000
b101101111 6
b10011000 4
b10011000 F
b10011000 ]
b10010000 %
b10010000 ?
b10010 -
1,
1)
#800000
0&
0,
0)
0(
#804000
b101100111 6
b10100000 4
b10100000 F
b10100000 ]
b10011000 %
b10011000 ?
b10011 -
1,
1)
#808000
0,
0)
#812000
b101011111 6
b10101000 4
b10101000 F
b10101000 ]
b10100000 %
b10100000 ?
b10100 -
1,
1)
#816000
0_
0,
0)
b10 5
0L
#820000
b101010111 6
b10110000 4
b10110000 F
b10110000 ]
b10101000 %
b10101000 ?
b10101 -
1,
1)
#824000
0,
0)
#828000
b101001111 6
b10111000 4
b10111000 F
b10111000 ]
b10110000 %
b10110000 ?
b10110 -
1,
1)
#832000
0,
0)
b0 5
0d
#836000
b101000111 6
b11000000 4
b11000000 F
b11000000 ]
b10111000 %
b10111000 ?
b10111 -
1,
1)
#840000
1&
0,
0)
1(
#844000
b100111111 6
b11001000 4
b11001000 F
b11001000 ]
b11000000 %
b11000000 ?
b11000 -
1,
1)
#848000
0,
0)
#852000
b100110111 6
b11010000 4
b11010000 F
b11010000 ]
b11001000 %
b11001000 ?
b11001 -
1,
1)
#856000
1_
0,
0)
b1 5
1L
#860000
b100101111 6
b11011000 4
b11011000 F
b11011000 ]
b11010000 %
b11010000 ?
b11010 -
1,
1)
#864000
0,
0)
#868000
b100100111 6
b11100000 4
b11100000 F
b11100000 ]
b11011000 %
b11011000 ?
b11011 -
1,
1)
#872000
0,
0)
b11 5
1d
