RTL/testbench/workbuddy/sim/idelaye3_stub.v
`timescale 1ns / 1ps
//////////////////////////////////////////////////////////////////////////////////
// Behavioral stub for IDELAYE3 (for iverilog simulation only).
// NOT synthesizable. Replaces the Xilinx UNISIM primitive so we can verify the
// loader FSM without Vivado. It latches CNTVALUEIN on the LOAD pulse (ASYNC) and
// applies a coarse delay = taps * 1ps to DATAIN so dout visibly lags din.
//////////////////////////////////////////////////////////////////////////////////
module IDELAYE3 #(
    parameter CASCADE       = "NONE",
    parameter DELAY_FORMAT  = "COUNT",
    parameter DELAY_SRC     = "DATAIN",
    parameter DELAY_TYPE    = "VAR_LOAD",
    parameter DELAY_VALUE   = 0,
    parameter IS_CLK_INVERTED = 1'b0,
    parameter IS_RST_INVERTED  = 1'b0,
    parameter real REFCLK_FREQUENCY = 300.0,
    parameter SIM_DEVICE    = "ULTRASCALE_PLUS",
    parameter UPDATE_MODE   = "ASYNC"
) (
    output wire        CASC_OUT,
    output wire [8:0]  CNTVALUEOUT,
    output wire        DATAOUT,
    input  wire        CASC_IN,
    input  wire        CASC_RETURN,
    input  wire        CE,
    input  wire        CLK,
    input  wire [8:0]  CNTVALUEIN,
    input  wire        DATAIN,
    input  wire        EN_VTC,
    input  wire        IDATAIN,
    input  wire        INC,
    input  wire        LOAD,
    input  wire        RST
);
    reg [8:0] taps;
    reg       dout_r;

    // ASYNC load: latch CNTVALUEIN on LOAD pulse.
    always @(posedge LOAD or posedge RST) begin
        if (RST)      taps <= 9'd0;
        else if (LOAD) taps <= CNTVALUEIN;
    end
    assign CNTVALUEOUT = taps;

    // Coarse behavioral delay: dout lags din by `taps` ps (1ps per tap in sim).
    always @(DATAIN or taps) begin
        #(taps) dout_r = (DELAY_SRC == "IDATAIN") ? IDATAIN : DATAIN;
    end
    assign DATAOUT = dout_r;

    assign CASC_OUT = 1'b0;
endmodule

RTL/testbench/workbuddy/src/dtc/idelay_dtc_top_single.v
`timescale 1ns / 1ps
//////////////////////////////////////////////////////////////////////////////////
// Module: idelay_dtc_top_single
//   IDELAYE3-based DTC, SINGLE STAGE, COUNT mode.
//   Drop-in replacement for lut_dtc_top / the previous 2-stage cascaded version.
//
// ============================================================================
// 2026-07-30 CHANGE: LOAD is now an EXTERNAL input
// ----------------------------------------------------------------------------
//   The module does NOT generate the LOAD pulse anymore. The user supplies
//   `load_i` from their own logic (e.g. a 12.5 MHz-domain controller). On each
//   `load_i` pulse the module commits ONE step (<=8 taps) toward `code`. The
//   VAR_LOAD single-load limit (<=8 taps) is guaranteed INSIDE the module; the
//   user only owns the load *timing*.
//
//   External contract:
//     * Drive `code` to the desired final tap value.
//     * Assert `load_i` (clean pulse, >=1 idelay_clk wide) to advance one step.
//       `idelay_busy`=1 means the module still has steps to go; stop pulsing
//       load_i when busy=0 (delay line frozen). A single load_i pulse = one step.
//     * (Optional) hold load_i high continuously while busy=1: the module steps
//       on every load_i rising edge until settled (each step <=8 taps).
//
//   Why this is glitch-free: `ld_value` is the value that WILL be loaded on the
//   NEXT load_i edge. While moving it equals `next_val` (combinational, already
//   stable), so the moment `load_i` rises the delay line latches the correct new
//   value in one shot — no setup gap, no multi-bit intermediate state sampled.
//
//   UPDATE_MODE = "ASYNC" (NOT "SYNC"): SYNC VAR_LOAD triggers REQP-1828 which
//   forces LOAD=GND, making loading impossible. ASYNC + a clean LOAD pulse is
//   legal and is what every working VAR_LOAD design uses.
//
//   Recommended clocking: drive `idelay_clk` from the SAME 12.5 MHz clock domain
//   as `din` (NOT from the IDELAYE3 DATAOUT — that is a feedback loop). The
//   12.5 MHz clock (80 ns period, >=40 ns low) gives a wide, relaxed LOAD window
//   ideal for ASYNC VAR_LOAD.
// ============================================================================
// WHY SINGLE-STAGE (and why the previous 2-stage fabric-chain version failed)
// ----------------------------------------------------------------------------
// * User measured on silicon: ONE IDELAYE3 already covers a full VCO period
//   (T_VCO = 3.2 ns; ~6.2 ps/tap on this slow corner -> 511*6.2 ps = 3.17 ns).
//   So a SINGLE stage is sufficient for the DTC range on this device.
// * A SINGLE IDELAYE3 has NO inter-stage half-select (256) glitch. The 256
//   glitch ONLY appears when two SEPARATE IDELAYE3s are chained (fabric or
//   dedicated cascade) and their internal half-select switches are not
//   perfectly time-aligned. Xilinx guarantees a glitch-free SINGLE IDELAYE3,
//   so single stage = glitch-free by construction.
// * No dedicated-cascade route -> no Route 35-19, no adjacent-BITSLICE LOC
//   constraint. One IDELAYE3 drops into any IOB BITSLICE.
// * Gain matches the EXISTING dtc_comp. dtc_comp computes
//     dtc_code = (e1 * gain) >> 11   (saturate 0..511 = 0..T_VCO)
//   with the assumption that 0..511 taps = 0..T_VCO at a 1x DTC gain. A single
//   stage has exactly that 1x gain, so NO digital re-mapping is needed. (The
//   2-stage version doubled the gain and would have broken the calibration.)
//
// ============================================================================
// CONSTRAINTS:
//   * create_clock on idelay_clk (12.5 MHz recommended) REQUIRED (drives ld_value
//     registration and the busy flag).
//   * COUNT mode: no IDELAYCTRL, no REFCLK, EN_VTC = 0.
//   * No LOC needed (single IDELAYE3 in any BITSLICE).
//   * REQP-1828 only applies to SYNC mode; ASYNC + external load_i is DRC-clean.
//////////////////////////////////////////////////////////////////////////////////

module idelay_dtc_top_single #(
    parameter N_TAP      = 512,       // unused (compat with lut_dtc_top)
    parameter CODE_WIDTH = 9
) (
    input  wire                   sys_clk,     // unused (compat)
    input  wire                   rst_n,       // active-LOW async reset
    input  wire                   din,         // signal to be delayed (from logic)
    input  wire [CODE_WIDTH-1:0]  code,        // target delay, 0..511 taps (external)
    input  wire                   cal_mode,    // unused (no manual cal) - compat
    input  wire [CODE_WIDTH-1:0]  cal_code,    // unused - compat
    input  wire                   dtc_sel,     // unused - compat
    input  wire                   vco_clk,     // unused - compat
    input  wire                   idelay_en,   // 0 = bypass (dout = din), 1 = use IDELAY
    input  wire                   idelay_clk,  // control clock (latches state, drives busy)
    input  wire                   load_i,      // EXTERNAL LOAD pulse (user-supplied)
    output wire                   idelay_load, // = load_i (passthrough, for observation)
    output wire                   idelay_busy, // 1 while loaded_code != code
    output wire                   dout,
    output wire [CODE_WIDTH-1:0]  cal_result,  // tied 0 (no manual cal)
    output wire                   cal_valid    // tied 0 (no manual cal)
);

    // ------------------------------------------------------------------
    // Stepwise ramp state (module-owned). Guarantees <= 8 taps per LOAD step.
    // ------------------------------------------------------------------
    reg [CODE_WIDTH-1:0] loaded_code;   // last committed value

    wire signed [CODE_WIDTH:0] diff = $signed({1'b0, code}) - $signed({1'b0, loaded_code});
    wire        moving = (diff != 0);

    // Saturating step, clamped to [-8, +8] (VAR_LOAD single-load limit).
    reg signed [4:0] step;
    always @(*) begin
        if      (diff >  8) step =  5'sd8;
        else if (diff < -8) step = -5'sd8;
        else                step = diff[4:0];
    end

    wire signed [CODE_WIDTH:0] next_s = $signed({1'b0, loaded_code}) + step;
    reg [CODE_WIDTH-1:0] next_val;
    always @(*) begin
        if      (next_s > $signed({1'b0, {CODE_WIDTH{1'b1}}})) next_val = {CODE_WIDTH{1'b1}};
        else if (next_s < 0)                                  next_val = {CODE_WIDTH{1'b0}};
        else                                                  next_val = next_s[CODE_WIDTH-1:0];
    end

    // Commit ONE step on each external load_i pulse (while moving).
    always @(posedge idelay_clk or negedge rst_n) begin
        if (~rst_n) loaded_code <= {CODE_WIDTH{1'b0}};
        else if (load_i && moving) loaded_code <= next_val;
    end

    // ld_value is the value that WILL be loaded on the next load_i edge:
    // while moving it is next_val (already stable, so a single load_i pulse
    // commits one correct step even in ASYNC level/edge mode); when settled it
    // holds loaded_code (delay line frozen).
    wire [CODE_WIDTH-1:0] ld_value;
    assign ld_value = moving ? next_val : loaded_code;

    assign idelay_load = load_i;
    assign idelay_busy = moving;

    // ------------------------------------------------------------------
    // Single IDELAYE3 (COUNT mode, VAR_LOAD, ASYNC update).
    // ------------------------------------------------------------------
    wire dout_int;

    IDELAYE3 #(
        .CASCADE("NONE"),
        .DELAY_FORMAT("COUNT"),
        .DELAY_SRC("DATAIN"),     // din comes from logic (not an IOB pad)
        .DELAY_TYPE("VAR_LOAD"),
        .DELAY_VALUE(0),
        .IS_CLK_INVERTED(1'b0),
        .IS_RST_INVERTED(1'b0),
        .REFCLK_FREQUENCY(300.0), // STA-only in COUNT mode (no physical REFCLK)
        .SIM_DEVICE("ULTRASCALE_PLUS"),
        .UPDATE_MODE("ASYNC")
    ) u_idelay (
        .CLK(idelay_clk),
        .CE(1'b0),
        .INC(1'b0),
        .CASC_IN(1'b0),
        .CASC_RETURN(1'b0),
        .CASC_OUT(),
        .IDATAIN(1'b0),
        .DATAIN(din),
        .LOAD(idelay_load),
        .CNTVALUEIN(ld_value),
        .CNTVALUEOUT(),
        .DATAOUT(dout_int),
        .EN_VTC(1'b0),
        .RST(~rst_n)
    );

    assign dout       = idelay_en ? dout_int : din;
    assign cal_result = {CODE_WIDTH{1'b0}};
    assign cal_valid  = 1'b0;

endmodule

RTL/testbench/workbuddy/sim/idelay_dtc_top_tb.v
`timescale 1ns / 1ps
//////////////////////////////////////////////////////////////////////////////////
// Testbench for idelay_dtc_top_single (EXTERNAL load_i version).
// Verifies: when `code` changes, an EXTERNAL load_i pulse stream makes the
// module step CNTVALUEIN toward `code` at <=8 taps/step, and the IDELAYE3 tap
// count (CNTVALUEOUT) follows `code`. This proves the delay tracks `code` under
// user-supplied LOAD (the bug we had was LOAD tied low -> zero delay).
//
// The external 12.5 MHz-domain controller is modeled simply: it pulses load_i
// (one rising edge per step) while idelay_busy=1, then stops. This matches real
// hardware where each load_i rising edge commits one module step.
//////////////////////////////////////////////////////////////////////////////////
module tb;
    reg            rst_n, din, idelay_en, idelay_clk, load_i;
    reg  [8:0]     code;
    wire           idelay_load, idelay_busy, dout, cal_valid;
    wire [8:0]     cal_result;
    wire [8:0]     taps;

    idelay_dtc_top_single dut (
        .sys_clk(1'b0), .rst_n(rst_n), .din(din), .code(code),
        .cal_mode(1'b0), .cal_code(9'd0), .dtc_sel(1'b0), .vco_clk(1'b0),
        .idelay_en(idelay_en), .idelay_clk(idelay_clk),
        .load_i(load_i), .idelay_load(idelay_load), .idelay_busy(idelay_busy),
        .dout(dout), .cal_result(cal_result), .cal_valid(cal_valid)
    );

    // Hierarchical probe into the stub's CNTVALUEOUT.
    assign taps = dut.u_idelay.CNTVALUEOUT;

    // 12.5 MHz control clock: #20 toggles -> 40 ns half-period (80 ns period),
    // high and low each >=40 ns (matches the user's DTC output clock spec).
    always #20 idelay_clk = ~idelay_clk;

    // External 12.5 MHz-domain controller: pulse load_i while busy.
    // toggle => one rising edge every 2 clocks => one module step per 2 clocks.
    reg load_toggle;
    always @(posedge idelay_clk or negedge rst_n) begin
        if (~rst_n) begin
            load_i <= 1'b0;
            load_toggle <= 1'b0;
        end else if (idelay_busy) begin
            load_toggle <= ~load_toggle;
            load_i      <= load_toggle;   // 1 during one phase, 0 during the other
        end else begin
            load_i      <= 1'b0;
            load_toggle <= 1'b0;
        end
    end

    // Toggle din so we can observe dout lagging.
    always #50 din = ~din;

    // Step-size check: whenever taps change, the jump must be <= 8.
    reg [8:0] prev_taps;
    reg       prev_valid;
    always @(posedge idelay_clk) begin
        if (prev_valid && (taps !== prev_taps)) begin
            if ((taps > prev_taps) && (taps - prev_taps > 9'd8))
                $display("ERR up step too big:   %0d -> %0d", prev_taps, taps);
            if ((prev_taps > taps) && (prev_taps - taps > 9'd8))
                $display("ERR down step too big: %0d -> %0d", prev_taps, taps);
        end
        prev_taps  <= taps;
        prev_valid <= 1'b1;
    end

    // Task: set code and wait (bounded) until the delay line settles (busy=0).
    task set_code;
        input [8:0] v;
        integer i;
        begin
            code = v;
            i = 0;
            while (idelay_busy && (i < 2000)) begin
                @(posedge idelay_clk);
                i = i + 1;
            end
            if (~idelay_busy)
                $display("SETTLED  code=%0d  taps=%0d  (waited %0d clk = %0d ns)",
                         v, taps, i, i*40);
            else
                $display("TIMEOUT  code=%0d  taps=%0d", v, taps);
        end
    endtask

    initial begin
        $dumpfile("idelay_dtc_tb.vcd");
        $dumpvars(0, tb);
        prev_valid = 0;
        idelay_clk = 0; rst_n = 0; din = 0; idelay_en = 1; code = 0; load_i = 0;
        #20 rst_n = 1;
        set_code(9'd100);    // 0 -> 100  (up)
        set_code(9'd50);     // 100 -> 50 (down)
        set_code(9'd300);    // 50 -> 300 (up, crosses 256 half-select boundary)
        set_code(9'd0);      // 300 -> 0  (down, crosses 256 again)
        #200;
        $display("DONE  (no ERR = every load step moved <=8 taps; SETTLED = delay tracks code)");
        $finish;
    end
endmodule

RTL/testbench/workbuddy/idelay_dtc_tb.vcd
$date
	Thu Jul 30 19:58:16 2026
$end
$version
	Icarus Verilog
$end
$timescale
	1ps
$end
$scope module tb $end
$var wire 9 ! cal_result [8:0] $end
$var wire 1 " cal_valid $end
$var wire 9 # taps [8:0] $end
$var wire 1 $ idelay_load $end
$var wire 1 % idelay_busy $end
$var wire 1 & dout $end
$var reg 9 ' code [8:0] $end
$var reg 1 ( din $end
$var reg 1 ) idelay_clk $end
$var reg 1 * idelay_en $end
$var reg 1 + load_i $end
$var reg 1 , load_toggle $end
$var reg 9 - prev_taps [8:0] $end
$var reg 1 . prev_valid $end
$var reg 1 / rst_n $end
$scope module dut $end
$var wire 9 0 cal_code [8:0] $end
$var wire 1 1 cal_mode $end
$var wire 9 2 cal_result [8:0] $end
$var wire 1 " cal_valid $end
$var wire 9 3 code [8:0] $end
$var wire 1 ( din $end
$var wire 1 4 dtc_sel $end
$var wire 1 % idelay_busy $end
$var wire 1 ) idelay_clk $end
$var wire 1 * idelay_en $end
$var wire 1 $ idelay_load $end
$var wire 1 + load_i $end
$var wire 1 / rst_n $end
$var wire 1 5 sys_clk $end
$var wire 1 6 vco_clk $end
$var wire 10 7 next_s [9:0] $end
$var wire 1 8 moving $end
$var wire 9 9 ld_value [8:0] $end
$var wire 1 : dout_int $end
$var wire 1 & dout $end
$var wire 10 ; diff [9:0] $end
$var parameter 32 < CODE_WIDTH $end
$var parameter 32 = N_TAP $end
$var reg 9 > loaded_code [8:0] $end
$var reg 9 ? next_val [8:0] $end
$var reg 5 @ step [4:0] $end
$scope module u_idelay $end
$var wire 1 A CASC_IN $end
$var wire 1 B CASC_OUT $end
$var wire 1 C CASC_RETURN $end
$var wire 1 D CE $end
$var wire 1 ) CLK $end
$var wire 9 E CNTVALUEIN [8:0] $end
$var wire 1 ( DATAIN $end
$var wire 1 F EN_VTC $end
$var wire 1 G IDATAIN $end
$var wire 1 H INC $end
$var wire 1 $ LOAD $end
$var wire 1 I RST $end
$var wire 1 : DATAOUT $end
$var wire 9 J CNTVALUEOUT [8:0] $end
$var parameter 32 K CASCADE $end
$var parameter 40 L DELAY_FORMAT $end
$var parameter 48 M DELAY_SRC $end
$var parameter 64 N DELAY_TYPE $end
$var parameter 32 O DELAY_VALUE $end
$var parameter 1 P IS_CLK_INVERTED $end
$var parameter 1 Q IS_RST_INVERTED $end
$var real 1 R REFCLK_FREQUENCY $end
$var parameter 120 S SIM_DEVICE $end
$var parameter 40 T UPDATE_MODE $end
$var reg 1 : dout_r $end
$var reg 9 U taps [8:0] $end
$upscope $end
$upscope $end
$scope task set_code $end
$var reg 9 V v [8:0] $end
$var integer 32 W i [31:0] $end
$upscope $end
$upscope $end
$enddefinitions $end
$comment Show the parameter values. $end
$dumpall
b100000101010011010110010100111001000011 T
b10101010100110001010100010100100100000101010011010000110100000101001100010001010101111101010000010011000101010101010011 S
r300 R
0Q
0P
b0 O
b101011001000001010100100101111101001100010011110100000101000100 N
b10001000100000101010100010000010100100101001110 M
b100001101001111010101010100111001010100 L
b1001110010011110100111001000101 K
b1000000000 =
b1001 <
$end
#0
$dumpvars
bx W
bx V
b0 U
b0 J
1I
0H
0G
0F
b0 E
0D
0C
0B
0A
b0 @
b0 ?
b0 >
b0 ;
0:
b0 9
08
b0 7
06
05
04
b0 3
b0 2
01
b0 0
0/
0.
bx -
0,
0+
1*
0)
0(
b0 '
0&
0%
0$
b0 #
0"
b0 !
$end
#20000
1.
b0 -
1,
b1000 9
b1000 E
b1000 ?
b1000 7
b1000 @
0I
b0 W
1%
18
b1100100 ;
b1100100 '
b1100100 3
b1100100 V
1/
1)
#40000
0)
#50000
1&
1:
1(
#60000
b1000 #
b1000 J
b1000 U
1$
1+
0,
b1 W
1)
#80000
0)
#100000
b10000 9
b10000 E
b10000 ?
b1000 -
0$
0+
1,
b1011100 ;
b10000 7
b1000 >
b10 W
1)
0(
#108000
0&
0:
#120000
0)
#140000
b10000 #
b10000 J
b10000 U
1$
1+
0,
b11 W
1)
#150000
1(
#156000
1&
1:
#160000
0)
#180000
b11000 9
b11000 E
b11000 ?
b10000 -
0$
0+
1,
b1010100 ;
b11000 7
b10000 >
b100 W
1)
#200000
0)
0(
#216000
0&
0:
#220000
b11000 #
b11000 J
b11000 U
1$
1+
0,
b101 W
1)
#240000
0)
#250000
1(
#260000
b100000 9
b100000 E
b100000 ?
b11000 -
0$
0+
1,
b1001100 ;
b100000 7
b11000 >
b110 W
1)
#274000
1&
1:
#280000
0)
#300000
b100000 #
b100000 J
b100000 U
1$
1+
0,
b111 W
1)
0(
#320000
0)
#324000
0&
0:
#340000
b101000 9
b101000 E
b101000 ?
b100000 -
0$
0+
1,
b1000100 ;
b101000 7
b100000 >
b1000 W
1)
#350000
1(
#360000
0)
#380000
b101000 #
b101000 J
b101000 U
1$
1+
0,
b1001 W
1)
#382000
1&
1:
#400000
0)
0(
#420000
b110000 9
b110000 E
b110000 ?
b101000 -
0$
0+
1,
b111100 ;
b110000 7
b101000 >
b1010 W
1)
#440000
0&
0)
0:
#450000
1(
#460000
b110000 #
b110000 J
b110000 U
1$
1+
0,
b1011 W
1)
#480000
0)
#490000
1&
1:
#500000
b111000 9
b111000 E
b111000 ?
b110000 -
0$
0+
1,
b110100 ;
b111000 7
b110000 >
b1100 W
1)
0(
#520000
0)
#540000
b111000 #
b111000 J
b111000 U
1$
1+
0,
b1101 W
1)
#548000
0&
0:
#550000
1(
#560000
0)
#580000
b1000000 9
b1000000 E
b1000000 ?
b111000 -
0$
0+
1,
b101100 ;
b1000000 7
b111000 >
b1110 W
1)
#600000
0)
0(
#620000
b1000000 #
b1000000 J
b1000000 U
1$
1+
0,
b1111 W
1)
#640000
0)
#650000
1(
#660000
b1001000 9
b1001000 E
b1001000 ?
b1000000 -
0$
0+
1,
b100100 ;
b1001000 7
b1000000 >
b10000 W
1)
#680000
0)
#684000
1&
1:
#700000
b1001000 #
b1001000 J
b1001000 U
1$
1+
0,
b10001 W
1)
0(
#720000
0)
#740000
b1010000 9
b1010000 E
b1010000 ?
b1001000 -
0$
0+
1,
b11100 ;
b1010000 7
b1001000 >
b10010 W
1)
#750000
1(
#760000
0)
#780000
b1010000 #
b1010000 J
b1010000 U
1$
1+
0,
b10011 W
1)
#800000
0)
0(
#820000
b1011000 9
b1011000 E
b1011000 ?
b1010000 -
0$
0+
1,
b10100 ;
b1011000 7
b1010000 >
b10100 W
1)
#840000
0)
#850000
1(
#860000
b1011000 #
b1011000 J
b1011000 U
1$
1+
0,
b10101 W
1)
#880000
0)
#900000
b1100000 9
b1100000 E
b1100000 ?
b1011000 -
0$
0+
1,
b1100 ;
b1100000 7
b1011000 >
b10110 W
1)
0(
#920000
0)
#940000
b1100000 #
b1100000 J
b1100000 U
1$
1+
0,
b10111 W
1)
#948000
0&
0:
#950000
1(
#960000
0)
#980000
b1100100 9
b1100100 E
b100 @
b1100100 ?
b1100000 -
0$
0+
1,
b100 ;
b1100100 7
b1100000 >
b11000 W
1)
#1000000
0)
0(
#1020000
b1100100 #
b1100100 J
b1100100 U
1$
1+
0,
b11001 W
1)
#1040000
0)
#1050000
1(
#1060000
b0 @
b1100100 ?
b1100100 -
0$
0+
1,
0%
08
b0 ;
b1100100 7
b1100100 >
b11010 W
1)
#1080000
0)
#1100000
0,
b1011100 9
b1011100 E
b1011100 ?
b1011100 7
b11000 @
1%
18
b1111001110 ;
b110010 '
b110010 3
b110010 V
b0 W
1)
0(
#1120000
0)
#1140000
1,
b1 W
1)
#1150000
1(
#1160000
0)
#1180000
b1011100 #
b1011100 J
b1011100 U
1$
1+
0,
b10 W
1)
#1200000
0)
0(
#1220000
b1010100 9
b1010100 E
b1010100 ?
b1011100 -
0$
0+
1,
b1111010110 ;
b1010100 7
b1011100 >
b11 W
1)
#1240000
0)
#1250000
1(
#1260000
b1010100 #
b1010100 J
b1010100 U
1$
1+
0,
b100 W
1)
#1280000
0)
#1300000
b1001100 9
b1001100 E
b1001100 ?
b1010100 -
0$
0+
1,
b1111011110 ;
b1001100 7
b1010100 >
b101 W
1)
0(
#1320000
0)
#1340000
b1001100 #
b1001100 J
b1001100 U
1$
1+
0,
b110 W
1)
#1350000
1(
#1360000
0)
#1380000
b1000100 9
b1000100 E
b1000100 ?
b1001100 -
0$
0+
1,
b1111100110 ;
b1000100 7
b1001100 >
b111 W
1)
#1400000
0)
0(
#1420000
b1000100 #
b1000100 J
b1000100 U
1$
1+
0,
b1000 W
1)
#1440000
0)
#1450000
1(
#1460000
b111100 9
b111100 E
b111100 ?
b1000100 -
0$
0+
1,
b1111101110 ;
b111100 7
b1000100 >
b1001 W
1)
#1480000
0)
#1500000
b111100 #
b111100 J
b111100 U
1$
1+
0,
b1010 W
1)
0(
#1520000
0)
#1540000
b110100 9
b110100 E
b110100 ?
b111100 -
0$
0+
1,
b1111110110 ;
b110100 7
b111100 >
b1011 W
1)
#1550000
1(
#1560000
0)
#1580000
b110100 #
b110100 J
b110100 U
1$
1+
0,
b1100 W
1)
#1600000
0)
0(
#1620000
b110010 9
b110010 E
b11110 @
b110010 ?
b110100 -
0$
0+
1,
b1111111110 ;
b110010 7
b110100 >
b1101 W
1)
#1640000
0)
#1650000
1(
#1660000
b110010 #
b110010 J
b110010 U
1$
1+
0,
b1110 W
1)
#1680000
0)
#1700000
b0 @
b110010 ?
b110010 -
0$
0+
1,
0%
08
b0 ;
b110010 7
b110010 >
b1111 W
1)
0(
#1720000
0)
#1740000
0,
b111010 9
b111010 E
b111010 ?
b111010 7
b1000 @
1%
18
b11111010 ;
b100101100 '
b100101100 3
b100101100 V
b0 W
1)
#1750000
1(
#1760000
0)
#1780000
1,
b1 W
1)
#1800000
0)
0(
#1820000
b111010 #
b111010 J
b111010 U
1$
1+
0,
b10 W
1)
#1840000
0)
#1850000
1(
#1860000
b1000010 9
b1000010 E
b1000010 ?
b111010 -
0$
0+
1,
b11110010 ;
b1000010 7
b111010 >
b11 W
1)
#1878000
1&
1:
#1880000
0)
#1900000
b1000010 #
b1000010 J
b1000010 U
1$
1+
0,
b100 W
1)
0(
#1920000
0)
#1940000
b1001010 9
b1001010 E
b1001010 ?
b1000010 -
0$
0+
1,
b11101010 ;
b1001010 7
b1000010 >
b101 W
1)
#1950000
1(
#1960000
0)
#1980000
b1001010 #
b1001010 J
b1001010 U
1$
1+
0,
b110 W
1)
#2000000
0)
0(
#2020000
b1010010 9
b1010010 E
b1010010 ?
b1001010 -
0$
0+
1,
b11100010 ;
b1010010 7
b1001010 >
b111 W
1)
#2040000
0)
#2050000
1(
#2060000
b1010010 #
b1010010 J
b1010010 U
1$
1+
0,
b1000 W
1)
#2080000
0)
#2100000
b1011010 9
b1011010 E
b1011010 ?
b1010010 -
0$
0+
1,
b11011010 ;
b1011010 7
b1010010 >
b1001 W
1)
0(
#2120000
0)
#2140000
b1011010 #
b1011010 J
b1011010 U
1$
1+
0,
b1010 W
1)
#2142000
0&
0:
#2150000
1(
#2160000
0)
#2180000
b1100010 9
b1100010 E
b1100010 ?
b1011010 -
0$
0+
1,
b11010010 ;
b1100010 7
b1011010 >
b1011 W
1)
#2200000
0)
0(
#2220000
b1100010 #
b1100010 J
b1100010 U
1$
1+
0,
b1100 W
1)
#2240000
0)
#2250000
1(
#2260000
b1101010 9
b1101010 E
b1101010 ?
b1100010 -
0$
0+
1,
b11001010 ;
b1101010 7
b1100010 >
b1101 W
1)
#2280000
0)
#2300000
b1101010 #
b1101010 J
b1101010 U
1$
1+
0,
b1110 W
1)
0(
#2320000
0)
#2340000
b1110010 9
b1110010 E
b1110010 ?
b1101010 -
0$
0+
1,
b11000010 ;
b1110010 7
b1101010 >
b1111 W
1)
#2350000
1(
#2360000
0)
#2380000
b1110010 #
b1110010 J
b1110010 U
1$
1+
0,
b10000 W
1)
#2400000
0)
0(
#2420000
b1111010 9
b1111010 E
b1111010 ?
b1110010 -
0$
0+
1,
b10111010 ;
b1111010 7
b1110010 >
b10001 W
1)
#2440000
0)
#2450000
1(
#2456000
1&
1:
#2460000
b1111010 #
b1111010 J
b1111010 U
1$
1+
0,
b10010 W
1)
#2480000
0)
#2500000
b10000010 9
b10000010 E
b10000010 ?
b1111010 -
0$
0+
1,
b10110010 ;
b10000010 7
b1111010 >
b10011 W
1)
0(
#2520000
0)
#2540000
b10000010 #
b10000010 J
b10000010 U
1$
1+
0,
b10100 W
1)
#2550000
1(
#2560000
0)
#2580000
b10001010 9
b10001010 E
b10001010 ?
b10000010 -
0$
0+
1,
b10101010 ;
b10001010 7
b10000010 >
b10101 W
1)
#2600000
0)
0(
#2620000
b10001010 #
b10001010 J
b10001010 U
1$
1+
0,
b10110 W
1)
#2640000
0)
#2650000
1(
#2660000
b10010010 9
b10010010 E
b10010010 ?
b10001010 -
0$
0+
1,
b10100010 ;
b10010010 7
b10001010 >
b10111 W
1)
#2680000
0)
#2700000
b10010010 #
b10010010 J
b10010010 U
1$
1+
0,
b11000 W
1)
0(
#2720000
0)
#2730000
0&
0:
#2740000
b10011010 9
b10011010 E
b10011010 ?
b10010010 -
0$
0+
1,
b10011010 ;
b10011010 7
b10010010 >
b11001 W
1)
#2750000
1(
#2760000
0)
#2780000
b10011010 #
b10011010 J
b10011010 U
1$
1+
0,
b11010 W
1)
#2800000
0)
0(
#2820000
b10100010 9
b10100010 E
b10100010 ?
b10011010 -
0$
0+
1,
b10010010 ;
b10100010 7
b10011010 >
b11011 W
1)
#2840000
0)
#2850000
1(
#2860000
b10100010 #
b10100010 J
b10100010 U
1$
1+
0,
b11100 W
1)
#2880000
0)
#2896000
1&
1:
#2900000
b10101010 9
b10101010 E
b10101010 ?
b10100010 -
0$
0+
1,
b10001010 ;
b10101010 7
b10100010 >
b11101 W
1)
0(
#2920000
0)
#2940000
b10101010 #
b10101010 J
b10101010 U
1$
1+
0,
b11110 W
1)
#2950000
1(
#2960000
0)
#2980000
b10110010 9
b10110010 E
b10110010 ?
b10101010 -
0$
0+
1,
b10000010 ;
b10110010 7
b10101010 >
b11111 W
1)
#3000000
0)
0(
#3020000
b10110010 #
b10110010 J
b10110010 U
1$
1+
0,
b100000 W
1)
#3040000
0)
#3050000
1(
#3060000
b10111010 9
b10111010 E
b10111010 ?
b10110010 -
0$
0+
1,
b1111010 ;
b10111010 7
b10110010 >
b100001 W
1)
#3080000
0)
#3100000
b10111010 #
b10111010 J
b10111010 U
1$
1+
0,
b100010 W
1)
0(
#3120000
0)
#3140000
b11000010 9
b11000010 E
b11000010 ?
b10111010 -
0$
0+
1,
b1110010 ;
b11000010 7
b10111010 >
b100011 W
1)
#3150000
1(
#3160000
0)
#3180000
b11000010 #
b11000010 J
b11000010 U
1$
1+
0,
b100100 W
1)
#3200000
0)
0(
#3220000
b11001010 9
b11001010 E
b11001010 ?
b11000010 -
0$
0+
1,
b1101010 ;
b11001010 7
b11000010 >
b100101 W
1)
#3240000
0)
#3250000
1(
#3260000
b11001010 #
b11001010 J
b11001010 U
1$
1+
0,
b100110 W
1)
#3280000
0)
#3300000
b11010010 9
b11010010 E
b11010010 ?
b11001010 -
0$
0+
1,
b1100010 ;
b11010010 7
b11001010 >
b100111 W
1)
0(
#3320000
0)
#3340000
b11010010 #
b11010010 J
b11010010 U
1$
1+
0,
b101000 W
1)
#3350000
1(
#3360000
0)
#3380000
b11011010 9
b11011010 E
b11011010 ?
b11010010 -
0$
0+
1,
b1011010 ;
b11011010 7
b11010010 >
b101001 W
1)
#3400000
0)
0(
#3420000
b11011010 #
b11011010 J
b11011010 U
1$
1+
0,
b101010 W
1)
#3440000
0)
#3450000
1(
#3460000
b11100010 9
b11100010 E
b11100010 ?
b11011010 -
0$
0+
1,
b1010010 ;
b11100010 7
b11011010 >
b101011 W
1)
#3480000
0)
#3500000
b11100010 #
b11100010 J
b11100010 U
1$
1+
0,
b101100 W
1)
0(
#3502000
0&
0:
#3520000
0)
#3540000
b11101010 9
b11101010 E
b11101010 ?
b11100010 -
0$
0+
1,
b1001010 ;
b11101010 7
b11100010 >
b101101 W
1)
#3550000
1(
#3560000
0)
#3580000
b11101010 #
b11101010 J
b11101010 U
1$
1+
0,
b101110 W
1)
#3600000
0)
0(
#3620000
b11110010 9
b11110010 E
b11110010 ?
b11101010 -
0$
0+
1,
b1000010 ;
b11110010 7
b11101010 >
b101111 W
1)
#3640000
0)
#3650000
1(
#3660000
b11110010 #
b11110010 J
b11110010 U
1$
1+
0,
b110000 W
1)
#3680000
0)
#3700000
b11111010 9
b11111010 E
b11111010 ?
b11110010 -
0$
0+
1,
b111010 ;
b11111010 7
b11110010 >
b110001 W
1)
0(
#3720000
0)
#3740000
b11111010 #
b11111010 J
b11111010 U
1$
1+
0,
b110010 W
1)
#3750000
1(
#3760000
0)
#3776000
1&
1:
#3780000
b100000010 9
b100000010 E
b100000010 ?
b11111010 -
0$
0+
1,
b110010 ;
b100000010 7
b11111010 >
b110011 W
1)
#3800000
0)
0(
#3820000
b100000010 #
b100000010 J
b100000010 U
1$
1+
0,
b110100 W
1)
#3840000
0)
#3850000
1(
